collect_framework/__init__.py
collect_framework/collect_framework.py
collect_framework-0.0.1.dist-info/LICENSE
collect_framework-0.0.1.dist-info/METADATA
collect_framework-0.0.1.dist-info/WHEEL
collect_framework-0.0.1.dist-info/top_level.txt
collect_framework-0.0.1.dist-info/RECORD
