Metadata-Version: 2.1
Name: collect-framework
Version: 0.0.1
Summary: Counter of unique chars
Home-page: https://git.foxminded.com.ua/Woiyter/task_5
Author: Woiyter
Author-email: iseefire3009@gmail.com
License: UNKNOWN
Platform: UNKNOWN
Classifier: Programming Language :: Python :: 3
Classifier: License :: OSI Approved :: MIT License
Classifier: Operating System :: OS Independent
Requires-Python: >=3.6
